[
    {
        "code": "BON",
        "color": "Ivory",
        "family": ["Bone broth", "Bone marrow"]
    },
    {
        "code": "EGG",
        "color": "Bisque",
        "family": ["Organic/Pastured Eggs"]
    },
    {
        "code": "FAT",
        "color": "LightGoldenRodYellow",
        "family": ["Beef Dripping", "Tallow", "Suet"]
    },
    {
        "code": "FIS",
        "color": "Gainsboro",
        "family": [
            "Small oily fish",
            "Sardines",
            "Mackerel",
            "Anchovies",
            "Herring",
            "Eel",
            "Pilchards",
            "Whitebait"
        ]
    },
    {
        "code": "INS",
        "color": "Wheat",
        "family": [
            "Insects",
            "Grubs",
            "Crickets",
            "Mealworms",
            "Larvae",
            "Grasshoppers",
            "Ants",
            "Cicadas"
        ]
    },
    {
        "code": "Liv",
        "color": "Pink",
        "family": ["Liver"]
    },
    {
        "code": "POU",
        "color": "LavenderBlush",
        "family": [
            "Organic/pasture fed poultry",
            "Chicken",
            "Turkey",
            "Duck",
            "Goose",
            "Pheasant",
            "Ostrich",
            "Partridge",
            "Pigeon",
            "Guinea Fowl",
            "Quail"
        ]
    },
    {
        "code": "RED",
        "color": "LightPink",
        "family": [
            "Grass/pasture fed red meat",
            "Beef",
            "Lamb",
            "Mutton",
            "Goat",
            "Venison",
            "Veal",
            "Pork"
        ]
    },
    {
        "code": "OFF",
        "color": "MistyRose",
        "family": [
            "Offal",
            "Kidney",
            "Heart",
            "Sweetbreads",
            "Tripe",
            "Spleen",
            "Tongue",
            "Pancreas",
            "Thymus",
            "Intestines",
            "Brains",
            "Testicles",
            "Organ meat"
        ]
    },
    {
        "code": "SHE",
        "color": "SeaShell",
        "family": [
            "Shellfish",
            "Snails",
            "Mussels",
            "Scallops",
            "Oysters",
            "Cockles",
            "Clams",
            "Crab",
            "Lobster",
            "Shrimp",
            "Prawn",
            "Crayfish",
            "Crawfish"
        ]
    }
]
